liner_tables/__init__.py
liner_tables/liner.py
liner_tables-0.1.1.dist-info/METADATA
liner_tables-0.1.1.dist-info/WHEEL
liner_tables-0.1.1.dist-info/top_level.txt
liner_tables-0.1.1.dist-info/RECORD
