Metadata-Version: 2.4
Name: liner_tables
Version: 0.1.1
Summary: Print table
Author: MrSanZz
Author-email: drownedmrsanzz@proton.me
Classifier: Programming Language :: Python :: 3
Classifier: License :: OSI Approved :: MIT License
Classifier: Operating System :: OS Independent
Requires-Python: >=3.6
Dynamic: author
Dynamic: author-email
Dynamic: classifier
Dynamic: description
Dynamic: description-content-type
Dynamic: requires-python
Dynamic: summary
